image_quantizer/__init__.py
image_quantizer/image.py
image_quantizer/palette.py
image_quantizer/version.py
image_quantizer/waveshare.py
image_quantizer-0.0.2.dist-info/METADATA
image_quantizer-0.0.2.dist-info/WHEEL
image_quantizer-0.0.2.dist-info/top_level.txt
image_quantizer-0.0.2.dist-info/RECORD
