Metadata-Version: 2.1
Name: image-quantizer
Version: 0.0.2
Summary: Convert image into quantized image compatible with Waveshare epaper display
Home-page: https://github.com/lobis/image-quantizer
Author: Luis Antonio Obis Aparicio
Author-email: luis.antonio.obis@gmail.com
License: UNKNOWN
Platform: UNKNOWN
Requires: Pillow
